README.rst
setup.py
async_downloader/__init__.py
async_downloader/download_engines.py
async_downloader/downloader.py
async_downloader/sources.py
async_downloader/utils.py
async_downloader.egg-info/PKG-INFO
async_downloader.egg-info/SOURCES.txt
async_downloader.egg-info/dependency_links.txt
async_downloader.egg-info/entry_points.txt
async_downloader.egg-info/requires.txt
async_downloader.egg-info/top_level.txt
async_downloader.egg-info/zip-safe
async_downloader/test/__init__.py
async_downloader/test/test_await.py
async_downloader/test/test_gen.py