Metadata-Version: 1.1
Name: async-downloader
Version: 0.2.1
Summary: mutil file download from custom sources. 
Home-page: https://www.github.com/ShichaoMa/async-downloader
Author: cn
Author-email: cnaafhvk@foxmail.com
License: MIT
Keywords: download async
Platform: UNKNOWN
Classifier: License :: OSI Approved :: MIT License
Classifier: Programming Language :: Python
Classifier: Intended Audience :: Developers
Classifier: Operating System :: OS Independent
